benchmark/CMakeLists.txt
benchmark/__init__.py
benchmark/speed_test_comparison.cpp
benchmark/speed_test_comparison.py
benchmark/speed_test_comparison_mkl.py
benchmark/speed_test_voxel_filter.py
benchmark/test.py
benchmark/test_data.py
point_cloud_registration/__init__.py
point_cloud_registration/caratheodory.py
point_cloud_registration/estimate_normals.py
point_cloud_registration/fast_voxelized_plane_icp.py
point_cloud_registration/icp.py
point_cloud_registration/kdtree.py
point_cloud_registration/math_tools.py
point_cloud_registration/ndt.py
point_cloud_registration/plane_icp.py
point_cloud_registration/registration.py
point_cloud_registration/voxel.py
point_cloud_registration/voxelized_plane_icp.py
point_cloud_registration-1.0.5.dist-info/LICENSE
point_cloud_registration-1.0.5.dist-info/METADATA
point_cloud_registration-1.0.5.dist-info/WHEEL
point_cloud_registration-1.0.5.dist-info/top_level.txt
point_cloud_registration-1.0.5.dist-info/RECORD
