Metadata-Version: 2.1
Name: point-cloud-registration
Version: 1.0.5
Summary: A fast and lightweight point cloud registration library implemented purely in Python.
Home-page: https://github.com/scomup/point-cloud-registration
Author: Liu Yang
Classifier: Programming Language :: Python :: 3
Classifier: License :: OSI Approved :: MIT License
Classifier: Operating System :: OS Independent
License-File: LICENSE
Requires-Dist: numpy
Requires-Dist: pykdtree
